<PubmedArticle>
<MedlineCitation Owner="NLM" Status="MEDLINE">
<PMID Version="1">11453096</PMID>
<DateCompleted>
<Year>2001</Year>
<Month>08</Month>
<Day>09</Day>
</DateCompleted>
<DateRevised>
<Year>2018</Year>
<Month>11</Month>
<Day>13</Day>
</DateRevised>
<Article PubModel="Print">
<Journal>
<ISSN IssnType="Print">0937-9827</ISSN>
<JournalIssue CitedMedium="Print">
<Volume>104</Volume>
<Issue>1</Issue>
<PubDate>
<Year>1990</Year>
<Month>Dec</Month>
</PubDate>
</JournalIssue>
<Title>International journal of legal medicine</Title>
<ISOAbbreviation>Int. J. Legal Med.</ISOAbbreviation>
</Journal>
<ArticleTitle>Fatal air embolism during female autoerotic practice.</ArticleTitle>
<Pagination>
<MedlinePgn>59-61</MedlinePgn>
</Pagination>
<Abstract>
<AbstractText>Air embolism has been described in pregnant women and is a classic cause of death during attempted abortion by syringing. Death was caused by the introduction of an amount of air sufficient to cause a substantial air lock in the heart, pulmonary trunk or arteries. If the surface of the placenta has been stripped by the syringe, venous spaces are opened and air can pass into the circulation. Orogenital sex with vaginal insufflation can also cause air embolism during pregnancy. We report a case of air embolism in a 40-year-old non-pregnant woman subsequent to vaginal insertion of a foreign body (carrot) for an autoerotic purpose. The mechanism is roughly similar to syringing, the foreign body acting like a piston to displace a sufficient amount of air. In the present case, the endometrium stripping was probably due to the presence of an intrauterine device. As such risks may often be encountered and as, to our knowledge, no similar case has previously been reported, we may speculate if such air embolisms are underdiagnosed or dissimulated by the partners when questioned by the medical rescue teams.</AbstractText>
</Abstract>
<AuthorList CompleteYN="Y">
<Author ValidYN="Y">
<LastName>Marc</LastName>
<ForeName>B</ForeName>
<Initials>B</Initials>
<AffiliationInfo>
<Affiliation>Service d'Anatomie et Cytologie Pathologiques/Médecine légale, Hĵpital Raymond Poincaré, Garches, France.</Affiliation>
</AffiliationInfo>
</Author>
<Author ValidYN="Y">
<LastName>Chadly</LastName>
<ForeName>A</ForeName>
<Initials>A</Initials>
</Author>
<Author ValidYN="Y">
<LastName>Durigon</LastName>
<ForeName>M</ForeName>
<Initials>M</Initials>
</Author>
</AuthorList>
<Language>eng</Language>
<PublicationTypeList>
<PublicationType UI="D002363">Case Reports</PublicationType>
<PublicationType UI="D016428">Journal Article</PublicationType>
</PublicationTypeList>
</Article>
<MedlineJournalInfo>
<Country>Germany</Country>
<MedlineTA>Int J Legal Med</MedlineTA>
<NlmUniqueID>9101456</NlmUniqueID>
<ISSNLinking>0937-9827</ISSNLinking>
</MedlineJournalInfo>
<CitationSubset>IM</CitationSubset>
<MeshHeadingList>
<MeshHeading>
<DescriptorName MajorTopicYN="N" UI="D000328">Adult</DescriptorName>
</MeshHeading>
<MeshHeading>
<DescriptorName MajorTopicYN="N" UI="D001344">Autopsy</DescriptorName>
<QualifierName MajorTopicYN="Y" UI="Q000379">methods</QualifierName>
</MeshHeading>
<MeshHeading>
<DescriptorName MajorTopicYN="N" UI="D004618">Embolism, Air</DescriptorName>
<QualifierName MajorTopicYN="Y" UI="Q000209">etiology</QualifierName>
<QualifierName MajorTopicYN="Y" UI="Q000473">pathology</QualifierName>
</MeshHeading>
<MeshHeading>
<DescriptorName MajorTopicYN="N" UI="D005260">Female</DescriptorName>
</MeshHeading>
<MeshHeading>
<DescriptorName MajorTopicYN="N" UI="D006801">Humans</DescriptorName>
</MeshHeading>
<MeshHeading>
<DescriptorName MajorTopicYN="N" UI="D008418">Masturbation</DescriptorName>
<QualifierName MajorTopicYN="Y" UI="Q000150">complications</QualifierName>
</MeshHeading>
</MeshHeadingList>
</MedlineCitation>
<PubmedData>
<History>
<PubMedPubDate PubStatus="pubmed">
<Year>1990</Year>
<Month>12</Month>
<Day>1</Day>
<Hour>0</Hour>
<Minute>0</Minute>
</PubMedPubDate>
<PubMedPubDate PubStatus="medline">
<Year>2001</Year>
<Month>8</Month>
<Day>10</Day>
<Hour>10</Hour>
<Minute>1</Minute>
</PubMedPubDate>
<PubMedPubDate PubStatus="entrez">
<Year>1990</Year>
<Month>12</Month>
<Day>1</Day>
<Hour>0</Hour>
<Minute>0</Minute>
</PubMedPubDate>
</History>
<PublicationStatus>ppublish</PublicationStatus>
<ArticleIdList>
<ArticleId IdType="pubmed">11453096</ArticleId>
</ArticleIdList>
<ReferenceList>
<Reference>
<Citation>Ann Emerg Med. 1986 May;15(5):576-84</Citation>
<ArticleIdList>
<ArticleId IdType="pubmed">3516022</ArticleId>
</ArticleIdList>
</Reference>
<Reference>
<Citation>Crit Care Med. 1988 Jul;16(7):729-30</Citation>
<ArticleIdList>
<ArticleId IdType="pubmed">3371050</ArticleId>
</ArticleIdList>
</Reference>
<Reference>
<Citation>Am J Med. 1985 Feb;78(2):333-6</Citation>
<ArticleIdList>
<ArticleId IdType="pubmed">3970057</ArticleId>
</ArticleIdList>
</Reference>
<Reference>
<Citation>J Forensic Sci. 1975 Jan;20(1):181-5</Citation>
<ArticleIdList>
<ArticleId IdType="pubmed">1117268</ArticleId>
</ArticleIdList>
</Reference>
<Reference>
<Citation>Obstet Gynecol. 1983 May;61(5):653-7</Citation>
<ArticleIdList>
<ArticleId IdType="pubmed">6835620</ArticleId>
</ArticleIdList>
</Reference>
<Reference>
<Citation>Am J Forensic Med Pathol. 1980 Jun;1(2):117-21</Citation>
<ArticleIdList>
<ArticleId IdType="pubmed">7246503</ArticleId>
</ArticleIdList>
</Reference>
<Reference>
<Citation>Am J Forensic Med Pathol. 1988 Mar;9(1):60-3</Citation>
<ArticleIdList>
<ArticleId IdType="pubmed">3354528</ArticleId>
</ArticleIdList>
</Reference>
<Reference>
<Citation>Am J Forensic Med Pathol. 1988 Sep;9(3):252-4</Citation>
<ArticleIdList>
<ArticleId IdType="pubmed">3177358</ArticleId>
</ArticleIdList>
</Reference>
<Reference>
<Citation>Leg Med Annu. 1977;:155-82</Citation>
<ArticleIdList>
<ArticleId IdType="pubmed">593035</ArticleId>
</ArticleIdList>
</Reference>
<Reference>
<Citation>Obstet Gynecol. 1967 Jul;30(1):127-30</Citation>
<ArticleIdList>
<ArticleId IdType="pubmed">6027480</ArticleId>
</ArticleIdList>
</Reference>
</ReferenceList>
</PubmedData>
</PubmedArticle>