<PubmedArticle>
<MedlineCitation Owner="NLM" Status="MEDLINE">
<PMID Version="1">18431067</PMID>
<DateCompleted>
<Year>2008</Year>
<Month>06</Month>
<Day>20</Day>
</DateCompleted>
<DateRevised>
<Year>2008</Year>
<Month>04</Month>
<Day>23</Day>
</DateRevised>
<Article PubModel="Print-Electronic">
<Journal>
<ISSN IssnType="Electronic">1421-9875</ISSN>
<JournalIssue CitedMedium="Internet">
<Volume>26</Volume>
<Issue>2</Issue>
<PubDate>
<Year>2008</Year>
</PubDate>
</JournalIssue>
<Title>Digestive diseases (Basel, Switzerland)</Title>
<ISOAbbreviation>Dig Dis</ISOAbbreviation>
</Journal>
<ArticleTitle>Intestinal malabsorption and skin diseases.</ArticleTitle>
<Pagination>
<MedlinePgn>167-74</MedlinePgn>
</Pagination>
<ELocationID EIdType="doi" ValidYN="Y">10.1159/000116775</ELocationID>
<Abstract>
<AbstractText>Several skin manifestations were described in patients affected by intestinal disorders. The development of skin diseases in these patients could be related to the impairment of intestinal absorption and motility, other than to immunological and hormonal changes. The growing evidence of the association between skin disorders and intestinal diseases suggests that the skin could be considered the 'mirror of the gut'.</AbstractText>
<CopyrightInformation>2008 S. Karger AG, Basel.</CopyrightInformation>
</Abstract>
<AuthorList CompleteYN="Y">
<Author ValidYN="Y">
<LastName>Abenavoli</LastName>
<ForeName>Ludovico</ForeName>
<Initials>L</Initials>
<AffiliationInfo>
<Affiliation>Institutes of Internal Medicine, Catholic University, Rome, Italy. l.abenavoli@yahoo.it</Affiliation>
</AffiliationInfo>
</Author>
<Author ValidYN="Y">
<LastName>Proietti</LastName>
<ForeName>Ilaria</ForeName>
<Initials>I</Initials>
</Author>
<Author ValidYN="Y">
<LastName>Vonghia</LastName>
<ForeName>Luisa</ForeName>
<Initials>L</Initials>
</Author>
<Author ValidYN="Y">
<LastName>Leggio</LastName>
<ForeName>Lorenzo</ForeName>
<Initials>L</Initials>
</Author>
<Author ValidYN="Y">
<LastName>Ferrulli</LastName>
<ForeName>Anna</ForeName>
<Initials>A</Initials>
</Author>
<Author ValidYN="Y">
<LastName>Capizzi</LastName>
<ForeName>Rodolfo</ForeName>
<Initials>R</Initials>
</Author>
<Author ValidYN="Y">
<LastName>Mirijello</LastName>
<ForeName>Antonio</ForeName>
<Initials>A</Initials>
</Author>
<Author ValidYN="Y">
<LastName>Cardone</LastName>
<ForeName>Silvia</ForeName>
<Initials>S</Initials>
</Author>
<Author ValidYN="Y">
<LastName>Malandrino</LastName>
<ForeName>Noemi</ForeName>
<Initials>N</Initials>
</Author>
<Author ValidYN="Y">
<LastName>Leso</LastName>
<ForeName>Veruska</ForeName>
<Initials>V</Initials>
</Author>
<Author ValidYN="Y">
<LastName>Rotoli</LastName>
<ForeName>Maurizio</ForeName>
<Initials>M</Initials>
</Author>
<Author ValidYN="Y">
<LastName>Amerio</LastName>
<ForeName>Pier Luigi</ForeName>
<Initials>PL</Initials>
</Author>
<Author ValidYN="Y">
<LastName>Gasbarrini</LastName>
<ForeName>Giovanni</ForeName>
<Initials>G</Initials>
</Author>
<Author ValidYN="Y">
<LastName>Addolorato</LastName>
<ForeName>Giovanni</ForeName>
<Initials>G</Initials>
</Author>
</AuthorList>
<Language>eng</Language>
<PublicationTypeList>
<PublicationType UI="D016428">Journal Article</PublicationType>
<PublicationType UI="D016454">Review</PublicationType>
</PublicationTypeList>
<ArticleDate DateType="Electronic">
<Year>2008</Year>
<Month>04</Month>
<Day>21</Day>
</ArticleDate>
</Article>
<MedlineJournalInfo>
<Country>Switzerland</Country>
<MedlineTA>Dig Dis</MedlineTA>
<NlmUniqueID>8701186</NlmUniqueID>
<ISSNLinking>0257-2753</ISSNLinking>
</MedlineJournalInfo>
<CitationSubset>IM</CitationSubset>
<MeshHeadingList>
<MeshHeading>
<DescriptorName MajorTopicYN="N" UI="D006801">Humans</DescriptorName>
</MeshHeading>
<MeshHeading>
<DescriptorName MajorTopicYN="N" UI="D008286">Malabsorption Syndromes</DescriptorName>
<QualifierName MajorTopicYN="Y" UI="Q000150">complications</QualifierName>
<QualifierName MajorTopicYN="N" UI="Q000453">epidemiology</QualifierName>
</MeshHeading>
<MeshHeading>
<DescriptorName MajorTopicYN="N" UI="D012871">Skin Diseases</DescriptorName>
<QualifierName MajorTopicYN="N" UI="Q000453">epidemiology</QualifierName>
<QualifierName MajorTopicYN="Y" UI="Q000209">etiology</QualifierName>
</MeshHeading>
</MeshHeadingList>
<NumberOfReferences>63</NumberOfReferences>
</MedlineCitation>
<PubmedData>
<History>
<PubMedPubDate PubStatus="pubmed">
<Year>2008</Year>
<Month>4</Month>
<Day>24</Day>
<Hour>9</Hour>
<Minute>0</Minute>
</PubMedPubDate>
<PubMedPubDate PubStatus="medline">
<Year>2008</Year>
<Month>6</Month>
<Day>21</Day>
<Hour>9</Hour>
<Minute>0</Minute>
</PubMedPubDate>
<PubMedPubDate PubStatus="entrez">
<Year>2008</Year>
<Month>4</Month>
<Day>24</Day>
<Hour>9</Hour>
<Minute>0</Minute>
</PubMedPubDate>
</History>
<PublicationStatus>ppublish</PublicationStatus>
<ArticleIdList>
<ArticleId IdType="pubmed">18431067</ArticleId>
<ArticleId IdType="pii">000116775</ArticleId>
<ArticleId IdType="doi">10.1159/000116775</ArticleId>
</ArticleIdList>
</PubmedData>
</PubmedArticle>