<PubmedArticle>
<MedlineCitation Owner="NLM" Status="MEDLINE">
<PMID Version="1">16915866</PMID>
<DateCompleted>
<Year>2006</Year>
<Month>12</Month>
<Day>01</Day>
</DateCompleted>
<DateRevised>
<Year>2019</Year>
<Month>06</Month>
<Day>06</Day>
</DateRevised>
<Article PubModel="Print">
<Journal>
<ISSN IssnType="Print">0272-9490</ISSN>
<JournalIssue CitedMedium="Print">
<Volume>60</Volume>
<Issue>4</Issue>
<PubDate>
<MedlineDate>2006 Jul-Aug</MedlineDate>
</PubDate>
</JournalIssue>
<Title>The American journal of occupational therapy : official publication of the American Occupational Therapy Association</Title>
<ISOAbbreviation>Am J Occup Ther</ISOAbbreviation>
</Journal>
<ArticleTitle>Occupational therapy activities and intervention techniques for clients with stroke in six rehabilitation hospitals.</ArticleTitle>
<Pagination>
<MedlinePgn>369-78</MedlinePgn>
</Pagination>
<Abstract>
<AbstractText Label="OBJECTIVE" NlmCategory="OBJECTIVE">To prospectively monitor occupational therapy activities and intervention techniques used during inpatient stroke rehabilitation in order to provide a description of current clinical practice.</AbstractText>
<AbstractText Label="METHODS" NlmCategory="METHODS">Data were collected prospectively from 954 clients with stroke receiving occupational therapy from six U.S. rehabilitation hospitals. Descriptive statistics summarized frequency, intensity, and duration of occupational therapy sessions; proportion of time spent in 16 therapeutic activities; and proportion of those activities that included any of 31 interventions.</AbstractText>
<AbstractText Label="RESULTS" NlmCategory="RESULTS">Clients received on average 11.8 days (SD = 7.2) of occupational therapy, with each session lasting on average 39.4 min (SD = 16.9). Upper-extremity control (22.9% of treatment time) and dressing (14.2% of treatment time) were the most frequently provided activities. Interventions provided most frequently during upper-extremity control activities were strengthening, motor learning, and postural awareness.</AbstractText>
<AbstractText Label="CONCLUSION" NlmCategory="CONCLUSIONS">Occupational therapy provided reflected an integration of treatment approaches. Upper-extremity control and basic activities of daily living were the most frequent activities. A small proportion of sessions addressed community integration.</AbstractText>
</Abstract>
<AuthorList CompleteYN="Y">
<Author ValidYN="Y">
<LastName>Latham</LastName>
<ForeName>Nancy K</ForeName>
<Initials>NK</Initials>
<AffiliationInfo>
<Affiliation>Health and Disability Research Institute, Boston University, 53 Bay State Road, Boston, Massachusetts 02215, USA. nlatham@bu.edu</Affiliation>
</AffiliationInfo>
</Author>
<Author ValidYN="Y">
<LastName>Jette</LastName>
<ForeName>Diane U</ForeName>
<Initials>DU</Initials>
</Author>
<Author ValidYN="Y">
<LastName>Coster</LastName>
<ForeName>Wendy</ForeName>
<Initials>W</Initials>
</Author>
<Author ValidYN="Y">
<LastName>Richards</LastName>
<ForeName>Lorie</ForeName>
<Initials>L</Initials>
</Author>
<Author ValidYN="Y">
<LastName>Smout</LastName>
<ForeName>Randall J</ForeName>
<Initials>RJ</Initials>
</Author>
<Author ValidYN="Y">
<LastName>James</LastName>
<ForeName>Roberta A</ForeName>
<Initials>RA</Initials>
</Author>
<Author ValidYN="Y">
<LastName>Gassaway</LastName>
<ForeName>Julie</ForeName>
<Initials>J</Initials>
</Author>
<Author ValidYN="Y">
<LastName>Horn</LastName>
<ForeName>Susan D</ForeName>
<Initials>SD</Initials>
</Author>
</AuthorList>
<Language>eng</Language>
<PublicationTypeList>
<PublicationType UI="D016428">Journal Article</PublicationType>
<PublicationType UI="D016448">Multicenter Study</PublicationType>
<PublicationType UI="D013485">Research Support, Non-U.S. Gov't</PublicationType>
<PublicationType UI="D013486">Research Support, U.S. Gov't, Non-P.H.S.</PublicationType>
</PublicationTypeList>
</Article>
<MedlineJournalInfo>
<Country>United States</Country>
<MedlineTA>Am J Occup Ther</MedlineTA>
<NlmUniqueID>7705978</NlmUniqueID>
<ISSNLinking>0272-9490</ISSNLinking>
</MedlineJournalInfo>
<CitationSubset>IM</CitationSubset>
<MeshHeadingList>
<MeshHeading>
<DescriptorName MajorTopicYN="N" UI="D000293">Adolescent</DescriptorName>
</MeshHeading>
<MeshHeading>
<DescriptorName MajorTopicYN="N" UI="D000328">Adult</DescriptorName>
</MeshHeading>
<MeshHeading>
<DescriptorName MajorTopicYN="N" UI="D000368">Aged</DescriptorName>
</MeshHeading>
<MeshHeading>
<DescriptorName MajorTopicYN="N" UI="D000369">Aged, 80 and over</DescriptorName>
</MeshHeading>
<MeshHeading>
<DescriptorName MajorTopicYN="N" UI="D005260">Female</DescriptorName>
</MeshHeading>
<MeshHeading>
<DescriptorName MajorTopicYN="N" UI="D006801">Humans</DescriptorName>
</MeshHeading>
<MeshHeading>
<DescriptorName MajorTopicYN="N" UI="D008297">Male</DescriptorName>
</MeshHeading>
<MeshHeading>
<DescriptorName MajorTopicYN="N" UI="D008875">Middle Aged</DescriptorName>
</MeshHeading>
<MeshHeading>
<DescriptorName MajorTopicYN="N" UI="D009788">Occupational Therapy</DescriptorName>
<QualifierName MajorTopicYN="Y" UI="Q000379">methods</QualifierName>
</MeshHeading>
<MeshHeading>
<DescriptorName MajorTopicYN="N" UI="D011446">Prospective Studies</DescriptorName>
</MeshHeading>
<MeshHeading>
<DescriptorName MajorTopicYN="Y" UI="D012047">Rehabilitation Centers</DescriptorName>
</MeshHeading>
<MeshHeading>
<DescriptorName MajorTopicYN="Y" UI="D000071939">Stroke Rehabilitation</DescriptorName>
</MeshHeading>
</MeshHeadingList>
</MedlineCitation>
<PubmedData>
<History>
<PubMedPubDate PubStatus="pubmed">
<Year>2006</Year>
<Month>8</Month>
<Day>19</Day>
<Hour>9</Hour>
<Minute>0</Minute>
</PubMedPubDate>
<PubMedPubDate PubStatus="medline">
<Year>2006</Year>
<Month>12</Month>
<Day>9</Day>
<Hour>9</Hour>
<Minute>0</Minute>
</PubMedPubDate>
<PubMedPubDate PubStatus="entrez">
<Year>2006</Year>
<Month>8</Month>
<Day>19</Day>
<Hour>9</Hour>
<Minute>0</Minute>
</PubMedPubDate>
</History>
<PublicationStatus>ppublish</PublicationStatus>
<ArticleIdList>
<ArticleId IdType="pubmed">16915866</ArticleId>
<ArticleId IdType="doi">10.5014/ajot.60.4.369</ArticleId>
</ArticleIdList>
</PubmedData>
</PubmedArticle>